{"cameraMode":{"drawMode":0,"name":"Shaded","section":"Shading Mode"},"sceneLighting":true,"audioPlay":false,"sceneViewState":{"m_AlwaysRefresh":false,"showFog":true,"showSkybox":true,"showFlares":true,"showImageEffects":true,"showParticleSystems":true,"showVisualEffectGraphs":true,"m_FxEnabled":true},"in2DMode":false,"pivot":{"x":468.59674072265627,"y":157.95985412597657,"z":-132.3974151611328},"rotation":{"x":-0.03988135978579521,"y":0.026710830628871919,"z":-0.0008780747302807868,"w":-0.9988865852355957},"size":3.8601503372192385,"orthographic":false}